recolonyzer/__init__.py
recolonyzer/__main__.py
recolonyzer/analysis.py
recolonyzer/filesystem.py
recolonyzer/image_processing.py
recolonyzer/utils.py
recolonyzer/commands/__init__.py
recolonyzer/commands/abstract.py
recolonyzer/commands/analyse.py
recolonyzer/commands/entrypoint.py
recolonyzer/commands/rename_images.py
recolonyzer-1.0.7.dist-info/LICENSE
recolonyzer-1.0.7.dist-info/METADATA
recolonyzer-1.0.7.dist-info/WHEEL
recolonyzer-1.0.7.dist-info/entry_points.txt
recolonyzer-1.0.7.dist-info/top_level.txt
recolonyzer-1.0.7.dist-info/RECORD
